fixed_that_for_you/__init__.py
fixed_that_for_you-1.0.0.dist-info/WHEEL
fixed_that_for_you-1.0.0.dist-info/METADATA
fixed_that_for_you-1.0.0.dist-info/RECORD
